{
  "num_tokens": 436,
  "num_sentences": 25,
  "num_lemmas": 349,
  "num_types": 107,
  "TTR": 0.307,
  "avg_sentence_length": 16.56,
  "Zipf_mean": 5.16,
  "Zipf_std": 1.59,
  "Zipf_freq": "5.16 ± 1.59",
  "percent_rare_words": 10.0,
  "Gulpease_index": 72.78,
  "num_function_words": 165,
  "num_function_words_pct": 37.8,
  "num_function_words_display": "165 (37.8%)",
  "num_content_words": 180,
  "num_content_words_pct": 41.3,
  "num_content_words_display": "180 (41.3%)",
  "num_verbs": 46,
  "num_verbs_pct": 10.6,
  "num_verbs_display": "46 (10.6%)",
  "num_adjectives": 11,
  "num_adjectives_pct": 2.5,
  "num_adjectives_display": "11 (2.5%)",
  "num_nouns": 100,
  "num_nouns_pct": 22.9,
  "num_nouns_display": "100 (22.9%)",
  "top_lemmas": [
    "il (8.5%)",
    "e (4.8%)",
    "a (3.9%)",
    "di (3.9%)",
    "Orso (3.4%)",
    "in (2.5%)",
    "tana (2.5%)",
    "essere (2.1%)",
    "uno (1.8%)",
    "Volpe (1.8%)",
    "buco (1.6%)",
    "Talpa (1.6%)",
    "si (1.4%)",
    "improvviso (1.4%)",
    "ma (1.4%)",
    "Rospo (1.4%)",
    "Formica (1.4%)",
    "tutto (1.1%)",
    "cascare (0.9%)",
    "iniziare (0.9%)"
  ],
  "top_bigrams": [
    "la tana (2.9%)",
    "tana di (2.6%)",
    "a l’ (1.7%)",
    "l’ improvviso (1.7%)",
    "di orso (1.7%)",
    "orso volpe (1.7%)",
    "e a (1.4%)",
    "buco ma (1.4%)",
    "volpe talpa (1.4%)",
    "e formica (1.4%)"
  ]
}