{
  "num_tokens": 458,
  "num_sentences": 20,
  "num_types": 230,
  "TTR": 0.502,
  "TTR_lemmas": 0.439,
  "avg_sentence_length": 24.2,
  "Zipf_mean": 5.36,
  "Zipf_std": 1.62,
  "Zipf_freq": "5.36 ± 1.62",
  "percent_rare_words": 11.28,
  "Gulpease_index": 59.09,
  "num_function_words": 239,
  "num_function_words_pct": 52.2,
  "num_function_words_display": "239 (52.2%)",
  "num_content_words": 219,
  "num_content_words_pct": 47.8,
  "num_content_words_display": "219 (47.8%)",
  "num_verbs": 64,
  "num_verbs_pct": 14.0,
  "num_verbs_display": "64 (14.0%)",
  "num_adjectives": 18,
  "num_adjectives_pct": 3.9,
  "num_adjectives_display": "18 (3.9%)",
  "num_nouns": 107,
  "num_nouns_pct": 23.4,
  "num_nouns_display": "107 (23.4%)",
  "top_lemmas": [
    "il (13.8%)",
    "di (5.7%)",
    "e (3.7%)",
    "a (3.7%)",
    "essere (3.1%)",
    "uno (2.6%)",
    "in (2.0%)",
    "mario (2.0%)",
    "si (1.7%)",
    "che (1.7%)",
    "casa (1.7%)",
    "non (1.3%)",
    "per (1.3%)",
    "suo (1.3%)",
    "da (0.9%)",
    "morire (0.9%)",
    "sentire (0.9%)",
    "loro (0.9%)",
    "proprio (0.7%)",
    "come (0.7%)"
  ],
  "top_bigrams": [
    "la casa (1.5%)",
    "di la (1.3%)",
    "a la (0.9%)",
    "in il (0.7%)",
    "a il (0.7%)",
    "i loro (0.7%)",
    "la valtellina (0.4%)",
    "un giorno (0.4%)",
    "di un (0.4%)",
    "il suo (0.4%)"
  ]
}